robust_fourier/AUTHORS.txt
robust_fourier/VERSION.txt
robust_fourier/__init__.py
robust_fourier/_utils/__init__.py
robust_fourier/_utils/_numba_helpers.py
robust_fourier/_utils/_validate.py
robust_fourier/_utils/_x_preprocessing.py
robust_fourier/chebyshev_polynomials/__init__.py
robust_fourier/chebyshev_polynomials/_class_interface.py
robust_fourier/chebyshev_polynomials/_func_interface.py
robust_fourier/chebyshev_polynomials/_numba_funcs.py
robust_fourier/chebyshev_polynomials/_numpy_funcs.py
robust_fourier/fourier_transform/__init__.py
robust_fourier/fourier_transform/_fft_utils.py
robust_fourier/hermite_functions/__init__.py
robust_fourier/hermite_functions/_approximations.py
robust_fourier/hermite_functions/_class_interface.py
robust_fourier/hermite_functions/_func_interface.py
robust_fourier/hermite_functions/_hermite_largest_extrema_spline.py
robust_fourier/hermite_functions/_hermite_largest_roots_spline.py
robust_fourier/hermite_functions/_hermite_tail_gauss_sigma_spline.py
robust_fourier/hermite_functions/_numba_funcs.py
robust_fourier/hermite_functions/_numpy_funcs.py
robust_fourier-0.1b0.dist-info/LICENSE
robust_fourier-0.1b0.dist-info/METADATA
robust_fourier-0.1b0.dist-info/WHEEL
robust_fourier-0.1b0.dist-info/top_level.txt
robust_fourier-0.1b0.dist-info/RECORD
