Metadata-Version: 2.1
Name: robust_fourier
Version: 0.1b0
Summary: Noise- and Outlier-Robust Fourier Transform with Hermite Functions in NumPy and Numba
Author-email: Niklas Zell <nik.zoe@web.de>
License: MIT License
Keywords: Fourier Transform,Hermite Functions,Robust,Noise,Outliers,NumPy,Numba
Requires-Python: >=3.9
License-File: LICENSE
Requires-Dist: numpy>=1.21.0
Requires-Dist: scipy>=1.7.0
Provides-Extra: dev
Requires-Dist: black>=24.4.0; extra == "dev"
Requires-Dist: coverage; extra == "dev"
Requires-Dist: esbonio; extra == "dev"
Requires-Dist: ipympl; extra == "dev"
Requires-Dist: isort[colors]>=5.13.0; extra == "dev"
Requires-Dist: jupyter; extra == "dev"
Requires-Dist: line-profiler; extra == "dev"
Requires-Dist: matplotlib; extra == "dev"
Requires-Dist: mypy>=1.11.0; extra == "dev"
Requires-Dist: numba>=0.55.0; extra == "dev"
Requires-Dist: pandas>=2.2.0; extra == "dev"
Requires-Dist: perfplot; extra == "dev"
Requires-Dist: pycodestyle>=2.12.0; extra == "dev"
Requires-Dist: pyright>=1.1.300; extra == "dev"
Requires-Dist: pytest; extra == "dev"
Requires-Dist: pytest-cov; extra == "dev"
Requires-Dist: pytest-xdist; extra == "dev"
Requires-Dist: ruff>=0.5.0; extra == "dev"
Requires-Dist: sympy; extra == "dev"
Requires-Dist: tqdm; extra == "dev"
Provides-Extra: examples
Requires-Dist: ipympl; extra == "examples"
Requires-Dist: jupyter; extra == "examples"
Requires-Dist: matplotlib; extra == "examples"
Provides-Extra: fast
Requires-Dist: numba>=0.55.0; extra == "fast"
Provides-Extra: git_ci
Requires-Dist: black>=24.4.0; extra == "git-ci"
Requires-Dist: coverage; extra == "git-ci"
Requires-Dist: isort[colors]>=5.13.0; extra == "git-ci"
Requires-Dist: matplotlib; extra == "git-ci"
Requires-Dist: mypy>=1.11.0; extra == "git-ci"
Requires-Dist: numba>=0.55.0; extra == "git-ci"
Requires-Dist: pandas>=2.2.0; extra == "git-ci"
Requires-Dist: pycodestyle>=2.12.0; extra == "git-ci"
Requires-Dist: pyright>=1.1.300; extra == "git-ci"
Requires-Dist: pytest; extra == "git-ci"
Requires-Dist: pytest-cov; extra == "git-ci"
Requires-Dist: pytest-xdist; extra == "git-ci"
Requires-Dist: ruff>=0.5.0; extra == "git-ci"
Requires-Dist: sympy; extra == "git-ci"
Requires-Dist: tqdm; extra == "git-ci"
